examples/fill_random.py
phare/__init__.py
phare/auth.py
phare/constants.py
phare/error.py
phare/lighthouse.py
phare/protocol.py
phare/serialize.py
venv/bin/rst2html.py
venv/bin/rst2html4.py
venv/bin/rst2html5.py
venv/bin/rst2latex.py
venv/bin/rst2man.py
venv/bin/rst2odt.py
venv/bin/rst2odt_prepstyles.py
venv/bin/rst2pseudoxml.py
venv/bin/rst2s5.py
venv/bin/rst2xetex.py
venv/bin/rst2xml.py
venv/bin/rstpep2html.py
phare-0.0.1.dist-info/LICENSE
phare-0.0.1.dist-info/METADATA
phare-0.0.1.dist-info/WHEEL
phare-0.0.1.dist-info/top_level.txt
phare-0.0.1.dist-info/RECORD
