Metadata-Version: 2.1
Name: phare
Version: 0.0.1
Summary: Asynchronous and ergonomic Project Lighthouse client library
License: MIT License
Project-URL: Homepage, https://github.com/fwcd/phare
Project-URL: Repository, https://github.com/fwcd/phare
Keywords: project-lighthouse
Classifier: Topic :: Utilities
Requires-Python: >=3.9
License-File: LICENSE
Requires-Dist: numpy <2,>=1.24
Requires-Dist: msgpack <2,>=1.0
Requires-Dist: websockets <13,>=12.0
